.bigmler
.bigmler_analyze
.bigmler_analyze_dir_stack
.bigmler_anomaly
.bigmler_anomaly_dir_stack
.bigmler_association
.bigmler_association_dir_stack
.bigmler_cluster
.bigmler_cluster_dir_stack
.bigmler_delete
.bigmler_delete_dir_stack
.bigmler_dir_stack
.bigmler_dirs
.bigmler_execute
.bigmler_execute_dir_stack
.bigmler_logistic_regression
.bigmler_logistic_regression_dir_stack
.bigmler_project
.bigmler_project_dir_stack
.bigmler_reify
.bigmler_reify_dir_stack
.bigmler_report
.bigmler_sample
.bigmler_sample_dir_stack
.bigmler_topic_model
.bigmler_topic_model_dir_stack
.bigmler_whizzml
.bigmler_whizzml_dir_stack
.noseids
bigmler/__init__.py
bigmler/anomaly_score.py
bigmler/bigmler.py
bigmler/centroid.py
bigmler/checkpoint.py
bigmler/command.py
bigmler/defaults.py
bigmler/dispatcher.py
bigmler/dispatchers.py
bigmler/dnprediction.py
bigmler/evaluation.py
bigmler/folderreader.py
bigmler/forecast.py
bigmler/labels.py
bigmler/logrprediction.py
bigmler/lrprediction.py
bigmler/parser.py
bigmler/pre_model_steps.py
bigmler/prediction.py
bigmler/projection.py
bigmler/reports.py
bigmler/resources.py
bigmler/sampleoutput.py
bigmler/sl_prediction.py
bigmler/topicdistribution.py
bigmler/train_reader.py
bigmler/tsevaluation.py
bigmler/tst_reader.py
bigmler/utf8recoder.py
bigmler/utils.py
bigmler/__pycache__/__init__.cpython-35.pyc
bigmler/__pycache__/anomaly_score.cpython-35.pyc
bigmler/__pycache__/bigmler.cpython-35.pyc
bigmler/__pycache__/centroid.cpython-35.pyc
bigmler/__pycache__/checkpoint.cpython-35.pyc
bigmler/__pycache__/command.cpython-35.pyc
bigmler/__pycache__/defaults.cpython-35.pyc
bigmler/__pycache__/dispatcher.cpython-35.pyc
bigmler/__pycache__/evaluation.cpython-35.pyc
bigmler/__pycache__/labels.cpython-35.pyc
bigmler/__pycache__/lrprediction.cpython-35.pyc
bigmler/__pycache__/parser.cpython-35.pyc
bigmler/__pycache__/pre_model_steps.cpython-35.pyc
bigmler/__pycache__/prediction.cpython-35.pyc
bigmler/__pycache__/reports.cpython-35.pyc
bigmler-5.10.3.dist-info/licenses/LICENSE
bigmler.egg-info/PKG-INFO
bigmler.egg-info/SOURCES.txt
bigmler.egg-info/dependency_links.txt
bigmler.egg-info/entry_points.txt
bigmler.egg-info/requires.txt
bigmler.egg-info/top_level.txt
bigmler-5.10.3.dist-info/METADATA
bigmler-5.10.3.dist-info/WHEEL
bigmler-5.10.3.dist-info/entry_points.txt
bigmler-5.10.3.dist-info/top_level.txt
bigmler-5.10.3.dist-info/RECORD
