Metadata-Version: 1.1
Name: bigmler
Version: 3.11.1
Summary: A command-line tool for BigML.io, the public BigML API
Home-page: https://bigml.com/developers
Author: The BigML Team
Author-email: bigml@bigml.com
License: http://www.apache.org/licenses/LICENSE-2.0
Download-URL: https://github.com/bigmlcom/bigmler
Platform: UNKNOWN
Classifier: Development Status :: 4 - Beta
Classifier: Intended Audience :: Developers
Classifier: License :: OSI Approved :: Apache Software License
Classifier: Natural Language :: English
Classifier: Operating System :: OS Independent
Classifier: Programming Language :: Python
Classifier: Programming Language :: Python :: 2
Classifier: Programming Language :: Python :: 2.7
Classifier: Programming Language :: Python :: 3
Classifier: Topic :: Software Development :: Libraries :: Python Modules
